feiertage/__init__.py
feiertage/easter.py
feiertage_de-0.1.6.dist-info/licenses/LICENSE
feiertage_de-0.1.6.dist-info/METADATA
feiertage_de-0.1.6.dist-info/WHEEL
feiertage_de-0.1.6.dist-info/top_level.txt
feiertage_de-0.1.6.dist-info/RECORD
