Metadata-Version: 2.4
Name: feiertage-de
Version: 0.1.6
Author-email: Michael Hohenstein <michael@hohenste.in>
Project-URL: Homepage, https://github.com/MitchiLaser/python-feiertage
Project-URL: Repository, https://github.com/MitchiLaser/python-feiertage
Classifier: Operating System :: OS Independent
Classifier: Programming Language :: Python :: 3
Classifier: Natural Language :: German
Classifier: Topic :: Office/Business
Classifier: Topic :: Office/Business :: Scheduling
Classifier: License :: OSI Approved :: GNU General Public License v3 (GPLv3)
Classifier: License :: OSI Approved :: GNU General Public License v3 or later (GPLv3+)
Requires-Python: >=3.7
License-File: LICENSE
Dynamic: license-file
